slambda_playground/__init__.py
slambda_playground/app.py
slambda_playground/assets/__init__.py
slambda_playground/assets/app.frontend
slambda_playground-0.0.2.dist-info/METADATA
slambda_playground-0.0.2.dist-info/WHEEL
slambda_playground-0.0.2.dist-info/RECORD
